apify/__init__.py
apify/_actor.py
apify/_charging.py
apify/_configuration.py
apify/_consts.py
apify/_crypto.py
apify/_models.py
apify/_proxy_configuration.py
apify/_utils.py
apify/log.py
apify/py.typed
apify/events/__init__.py
apify/events/_apify_event_manager.py
apify/events/_types.py
apify/events/py.typed
apify/request_loaders/__init__.py
apify/request_loaders/_apify_request_list.py
apify/request_loaders/py.typed
apify/scrapy/__init__.py
apify/scrapy/_actor_runner.py
apify/scrapy/_async_thread.py
apify/scrapy/_logging_config.py
apify/scrapy/py.typed
apify/scrapy/requests.py
apify/scrapy/scheduler.py
apify/scrapy/utils.py
apify/scrapy/extensions/__init__.py
apify/scrapy/extensions/_httpcache.py
apify/scrapy/middlewares/__init__.py
apify/scrapy/middlewares/apify_proxy.py
apify/scrapy/middlewares/py.typed
apify/scrapy/pipelines/__init__.py
apify/scrapy/pipelines/actor_dataset_push.py
apify/scrapy/pipelines/py.typed
apify/storage_clients/__init__.py
apify/storage_clients/py.typed
apify/storage_clients/_apify/__init__.py
apify/storage_clients/_apify/_alias_resolving.py
apify/storage_clients/_apify/_api_client_creation.py
apify/storage_clients/_apify/_dataset_client.py
apify/storage_clients/_apify/_key_value_store_client.py
apify/storage_clients/_apify/_models.py
apify/storage_clients/_apify/_request_queue_client.py
apify/storage_clients/_apify/_request_queue_shared_client.py
apify/storage_clients/_apify/_request_queue_single_client.py
apify/storage_clients/_apify/_storage_client.py
apify/storage_clients/_apify/_utils.py
apify/storage_clients/_apify/py.typed
apify/storage_clients/_file_system/__init__.py
apify/storage_clients/_file_system/_key_value_store_client.py
apify/storage_clients/_file_system/_storage_client.py
apify/storage_clients/_smart_apify/__init__.py
apify/storage_clients/_smart_apify/_storage_client.py
apify/storages/__init__.py
apify/storages/py.typed
apify-3.1.0.dist-info/METADATA
apify-3.1.0.dist-info/WHEEL
apify-3.1.0.dist-info/licenses/LICENSE
apify-3.1.0.dist-info/RECORD
