Metadata-Version: 2.4
Name: apify
Version: 3.1.0
Summary: Apify SDK for Python
Project-URL: Apify Homepage, https://apify.com
Project-URL: Changelog, https://docs.apify.com/sdk/python/docs/changelog
Project-URL: Discord, https://discord.com/invite/jyEM2PRvMU
Project-URL: Documentation, https://docs.apify.com/sdk/python/docs/overview/introduction
Project-URL: Homepage, https://docs.apify.com/sdk/python/
Project-URL: Issue Tracker, https://github.com/apify/apify-sdk-python/issues
Project-URL: Release Notes, https://docs.apify.com/sdk/python/docs/upgrading/upgrading-to-v2
Project-URL: Source Code, https://github.com/apify/apify-sdk-python
Author-email: "Apify Technologies s.r.o." <support@apify.com>
License:                                  Apache License
License-File: LICENSE
Keywords: apify,automation,chrome,crawlee,crawler,headless,scraper,scraping,sdk
Classifier: Development Status :: 5 - Production/Stable
Classifier: Environment :: Console
Classifier: Intended Audience :: Developers
Classifier: License :: OSI Approved :: Apache Software License
Classifier: Operating System :: OS Independent
Classifier: Programming Language :: Python :: 3.10
Classifier: Programming Language :: Python :: 3.11
Classifier: Programming Language :: Python :: 3.12
Classifier: Programming Language :: Python :: 3.13
Classifier: Programming Language :: Python :: 3.14
Classifier: Topic :: Software Development :: Libraries
Requires-Python: >=3.10
Requires-Dist: apify-client<3.0.0,>=2.3.0
Requires-Dist: apify-shared<3.0.0,>=2.0.0
Requires-Dist: cachetools>=5.5.0
Requires-Dist: crawlee<2.0.0,>=1.0.4
Requires-Dist: cryptography>=42.0.0
Requires-Dist: impit>=0.8.0
Requires-Dist: lazy-object-proxy>=1.11.0
Requires-Dist: more-itertools>=10.2.0
Requires-Dist: typing-extensions>=4.1.0
Requires-Dist: websockets>=14.0
Requires-Dist: yarl>=1.18.0
Provides-Extra: scrapy
Requires-Dist: scrapy>=2.11.0; extra == 'scrapy'
